{
   "alias" : "H.R. Burdick, Horace R Burdick",
   "hasLandingPage": true,
   "name" : "Horace Robbin Burdick",
   "metaTitle": "Horace Robbin Burdick Artist Paintings For Sale",
   "metaDescription": "Experience Horace Robbin Burdick's artistic journey. Acquire his captivating paintings for sale, enriching your collection with unique beauty.",
   "paintings" : [
      "horace_robbin_burdick_coolidge-html"
   ],
   "slug" : "horace_robbin_burdick_artwork-html",
   "tinyDescription" : "American 1844 - 1942"
}
