{
   "alias" : "William Schmedtgen",
   "hasLandingPage": true,
   "name" : "William Hermann Schmedtgen",
   "metaTitle": "William Hermann Schmedtgen Paintings For Sale",
   "metaDescription": "Explore William Hermann Schmedtgen's captivating paintings for sale. Elevate your collection with his emotive artistry and exquisite compositions.",
   "paintings" : [
      "william_herman_schmedtgen_bass-html"
   ],
   "slug" : "william_hermann_schmedtgen_artwork-html",
   "tinyDescription" : "American, 1862 - 1936"
}
