{
  "date": "2024-08-30T10:39:41.908Z",
  "slug": "art_lovers_niche_90.html",
  "body": "<table width=\"100%\" border=\"0\" cellspacing=\"0\" cellpadding=\"0\">\n  <tbody>\n\n\t<tr>\n           <td width=\"100%\" align=\"center\" bgcolor=\"#f5f1ec\" class=\"column\" style=\"padding: 0px;\">\n             <table width=\"100%\" class=\"content\" style=\"border-spacing:0;font-size:15px;font-weight:normal;text-align:center;\" role=\"presentation\">\n               <tr>\n                 <td style=\"padding:16px 16px 0px 16px;\">\n                  <h1 style=\"font-size: 22px; line-height: 22px; Margin: 0; border-bottom: 1px solid #ccc;padding-bottom: 8px;\">James Hamilton </h1>\n                 </td>\n               </tr>\n             </table>\n           </td>\n         </tr>\n\t\t   \n\t\t   \t\n\n\t\t   \t\t   \n\t\t   <tr>\n           <td style=\"padding:0;\" bgcolor=\"#f5f1ec\">\n             <table width=\"100%\" style=\"border-spacing:0;\" role=\"presentation\">\n\n\t\t   \t\t   \n\t\t   <tr>\n           <td style=\"padding:0;\" bgcolor=\"#f5f1ec\">\n             <table width=\"100%\" style=\"border-spacing:0;\" role=\"presentation\">\n               <tr>\n                 <td bgcolor=\"#f5f1ec\" align=\"center\" style=\"padding: 16px;\">\n                   <a href=\"https://www.bedfordfineartgallery.com/james_hamilton_ships_off_the_coast.html\" target=\"_blank\">\n                     <img src=\"https://res.cloudinary.com/dg6smdedp/image/upload/v1724860840/Hamilton_Hamilton_Ships_Off_the_Coast_IMG_2225-1_sm_cr_fr_azbkcn_gqolg1.jpg\" alt=\"Art is Smart\" style=\"width: 100%; height: auto; max-width: 500px; display: block; vertical-align:top;border:0;\">\n                   </a>\n                 </td>\n\t\t\t\n               </tr>\n             </table>\n           </td>\n         </tr>\n             </table>\n           </td>\n         </tr>\n\t\t   \n\t\t   <tr>\n           <td width=\"100%\" align=\"center\" bgcolor=\"#f5f1ec\" class=\"column\" style=\"padding: 0px;\">\n             <table width=\"100%\" class=\"content\" style=\"border-spacing:0;font-size:15px;font-weight:normal;text-align:left;\" role=\"presentation\">\n               <tr>\n                 <td style=\"padding:16px 16px 0px 16px;\">\n                  <p style=\"font-size: 16px; line-height: 22px; Margin: 0; padding-bottom: 8px;\">Hamilton was born near Belfast, Ireland; however, in 1832, the family came to the United States and settled in Philadelphia, Pennsylvania. He showed an early interest in art and was helped by a family friend, who provided the means for him to take instruction. He was encouraged by John Nagel, John Sartain, Thomas Birch and other Philadelphia artists to sell a few pictures and practice his craft on stone and wood to generate income while studying art. Aside from this limited art instruction and advice, Hamilton was largely self-taught. Cira 1840 became a teacher of drawing in Philadelphia—his pupils included Peter and Thomas Moran. </p>\n                 </td>\n               </tr>\n             </table>\n           </td>\n         </tr>\n\t\t   \n\t\t   \t<tr>\n           <td width=\"100%\" align=\"center\" bgcolor=\"#f5f1ec\" class=\"column\" style=\"padding: 0px;\">\n             <table width=\"100%\" class=\"content\" style=\"border-spacing:0;font-size:15px;font-weight:bold;text-align:center;\" role=\"presentation\">\n               <tr>\n                 <td style=\"padding:30px 16px 30px 16px;\">\n                  <p style=\"font-size: 20px; line-height: 22px; Margin: 0;\"> <a href=\"https://www.bedfordfineartgallery.com/james_hamilton_ships_off_the_coast.html\" target=\"_blank\" style=\"color: #FFF; background-color: #742924; text-decoration: none; display: inline-block;padding: 10px 15px; text-align: center; Margin: 0 auto; border-radius: 6px;\">Read More </a></p>\n                 </td>\n               </tr>\n             </table>\n           </td>\n         </tr>\n\t\t   \n\t\t     <tr>\n           <td width=\"100%\" align=\"center\" bgcolor=\"#fff\" class=\"column\" style=\"padding: 32px 0px 0px 0px;\">\n             <table width=\"90%\" class=\"content\" style=\"border-spacing:0;font-size:15px;font-weight:bold;text-align:center;\" role=\"presentation\">\n               <tr>\n                 <td style=\"padding:16px; border-top: 1px solid #ccc; border-bottom: 1px solid #ccc;\">\n                  <p style=\"font-size: 16px; line-height: 22px; Margin: 0;\"><q>Art is an experience, not an object.</q></p>\n\t\t\t\t\t   <p style=\"font-size: 15px; line-height: 22px; Margin: 0;padding-top:7px;\">- Robert Motherwell</p>\n                 </td>\n               </tr>\n             </table>\n           </td>\n         </tr>\n\t\t   \n\t\t\n\t\t   \n\t\t   \t<tr>\n           <td width=\"100%\" align=\"center\" bgcolor=\"#fff\" class=\"column\" style=\"padding: 0px;\">\n             <table width=\"100%\" class=\"content\" style=\"border-spacing:0;font-size:15px;font-weight:bold;text-align:center;\" role=\"presentation\">\n               <tr>\n                 <td style=\"padding:30px 16px 30px 16px;\">\n                  <p style=\"font-size: 20px; line-height: 22px; Margin: 0;\"> <a href=\"https://www.bedfordfineartgallery.com/Artists--Bios.html\" target=\"_blank\" style=\"color: #FFF; background-color: #742924; text-decoration: none; display: inline-block;padding: 10px 15px; text-align: center; Margin: 0 auto; border-radius: 6px;\">Find a new true love!</a></p>\n                 </td>\n               </tr>\n             </table>\n           </td>\n         </tr>\n\n</tbody>\n</table>",
  "metaTitle": "19th Century art from Bedford Fine Art Gallery",
  "metaDescription": "19th Century art from Bedford Fine Art Gallery",
  "preview": "Hamilton was born near Belfast, Ireland; however, in 1832, the family came to the United States and settled in Philadelphia, Pennsylvania."
}